pydozeoff
