Metadata-Version: 1.0
Name: pydozeoff
Version: 0.1.3
Summary: Web-based presentation engine for programmers
Home-page: http://github.com/danielfm/pydozeoff
Author: Daniel Fernandes Martins
Author-email: daniel@destaquenet.com
License: BSD
Keywords: web,presentation,slideshow,talk,engine,python,s5
Platform: Any
Classifier: Development Status :: 3 - Alpha
Classifier: Environment :: Console
Classifier: Environment :: Web Environment
Classifier: Intended Audience :: Developers
Classifier: License :: OSI Approved :: BSD License
Classifier: Natural Language :: English
Classifier: Operating System :: OS Independent
Classifier: Programming Language :: Python
Classifier: Programming Language :: Python :: 2.5
Classifier: Topic :: Communications
Classifier: Topic :: Multimedia :: Graphics :: Presentation
